nistchempy/__init__.py
nistchempy/compound.py
nistchempy/compound_list.py
nistchempy/requests.py
nistchempy/search.py
nistchempy/utils.py
nistchempy/data/nist_data.zip
nistchempy/parsing/__init__.py
nistchempy/parsing/compound.py
nistchempy/parsing/gas_chromatography.py
nistchempy-1.0.4.dist-info/licenses/LICENSE.md
nistchempy-1.0.4.dist-info/METADATA
nistchempy-1.0.4.dist-info/WHEEL
nistchempy-1.0.4.dist-info/top_level.txt
nistchempy-1.0.4.dist-info/RECORD
